{"title": "PEA   บรรเทาความเดือดร้อนผู้ใช้ไฟฟ้าที่ประสบภัยน้ำท่วมในพื้นที่ภาคเหนือ   และภาคตะวันออกเฉียงเหนือ", "url": "https://www.thairath.co.th/news/local/2816864", "tags": ["news", "local", "2816864"], "publish_date": "27 ก.ย. 2567 17:16 น.", "ner_obj": {"ner": {"entities": [{"type": "LOCATION", "value": "ภาคเหนือและภาคตะวันออกเฉียงเหนือ"}, {"type": "DATE", "value": "24  กันยายน 2567 เดือน กันยายน เดือน ตุลาคม 2567 เดือน กันยายน 2567 เดือน ตุลาคม 2567"}, {"type": "PERCENT", "value": "ร้อยละ30"}, {"type": "PHONE", "value": "1129"}, {"type": "TIME", "value": "ตลอด24ชั่วโมง"}, {"type": "ORGANIZATION", "value": "<unk>ews"}], "language": "th"}, "num_of_characters": 759, "num_of_limited_characters": 759, "num_of_limited_words": 176, "num_of_words": 176, "original_message": "PEA บรรเทาความเดือดร้อนผู้ใช้ไฟฟ้าที่ประสบภัยน้ำท่วมในพื้นที่ภาคเหนือ และภาคตะวันออกเฉียงเหนือ ตามมติคณะรัฐมนตรี (ครม.) วันที่ 24 กันยายน 2567 เห็นชอบมาตรการช่วยเหลือค่าไฟฟ้าแก่ผู้ใช้ไฟฟ้าประเภทบ้านอยู่อาศัยและกิจการขนาดเล็ก (ไม่รวมส่วนราชการและรัฐวิสาหกิจ) ที่อยู่ในพื้นที่ที่หน่วยงานราชการประกาศให้เป็นพื้นที่ประสบภัยพิบัติจากอุทกภัย สําหรับค่าไฟฟ้าประจําเดือนกันยายนและเดือนตุลาคม 2567 เพื่อช่วยบรรเทาความเดือดร้อนและลดภาระค่าไฟฟ้าให้กับผู้ประสบภัย โดยมีรายละเอียดดังนี้เดือนกันยายน 2567 : ไม่เรียกเก็บค่าไฟฟ้า กรณีชำระแล้ว PEA จะดำเนินการคืนเงินโดยนำไปหักลดจากค่าไฟฟ้าเดือนถัดๆ ไปเดือนตุลาคม 2567 : ให้ส่วนลดค่าไฟฟ้าร้อยละ 30 ก่อนคํานวณภาษีมูลค่าเพิ่มทั้งนี้ ผู้ใช้ไฟฟ้าสามารถสอบถามข้อมูลเพิ่มเติมได้ที่โทร. 1129 PEA Contact Center ตลอด 24 ชั่วโมง#PRNews "}}