{
    "title": "ท่วมซ้ำซาก",
    "url": "https://www.thairath.co.th/news/local/2812625",
    "publish_date": "2024-09-05",
    "content": "ท่วมซ้ำซาก ชาวบ้านในชุมชนมัสยิดท่าอิฐ ต.ท่าอิฐ อ.ปากเกร็ด จ.นนทบุรี ต้องขนข้าวของเครื่องใช้ไฟฟ้าหนีน้ำท่วม หลังเขื่อนเจ้าพระยาระบายน้ำ ลงท้ายเขื่อน ทำให้แม่น้ำเจ้าพระยาเพิ่มสูงอย่างรวดเร็ว ประกอบกับเป็น ช่วงที่น้ำทะเลหนุนสูง ทำให้น้ำเอ่อท่วม บ้านติดต่อกันหลายวัน ล่าสุดระดับน้ำ สูงเกือบครึ่งเมตรเดือดร้อนไปทั่ว.",
    "location": "นนทบุรี",
    "duration_ms": 174.32427406311035
}